CHANGES
LICENSE
MANIFEST.in
README.rst
flask_cachual.py
setup.cfg
setup.py
Flask_Cachual.egg-info/PKG-INFO
Flask_Cachual.egg-info/SOURCES.txt
Flask_Cachual.egg-info/dependency_links.txt
Flask_Cachual.egg-info/not-zip-safe
Flask_Cachual.egg-info/requires.txt
Flask_Cachual.egg-info/top_level.txt
docs/.gitignore
docs/Makefile
docs/conf.py
docs/index.rst